{"name":"Notify stakeholders on changes with Discord on autopilot","nodes":[{"parameters":{"httpMethod":"POST","path":"wf09203-order","options":{}},"type":"n8n-nodes-base.webhook","typeVersion":2,"position":[-270,400],"id":"371b56aa-e691-4a98-8627-4f2d3d6690c3","name":"Receive Inbound Webhook","webhookId":"28044b1d-c53c-4b5e-b9b9-b6ad666b4639"},{"parameters":{"conditions":{"options":{"caseSensitive":true,"leftValue":"","typeValidation":"strict","version":2},"conditions":[{"id":"28612bc8-635b-4b95-9d37-54fe76414b21","leftValue":"={{ $json.email }}","rightValue":"","operator":{"type":"string","operation":"notEmpty"}}],"combinator":"and"}},"type":"n8n-nodes-base.if","typeVersion":2.2,"position":[54,400],"id":"46c1ca64-714c-40d7-a84e-d094dfd3a049","name":"Required Fields Present?"},{"parameters":{"errorType":"errorMessage","errorMessage":"Missing required field 'email' on incoming order."},"type":"n8n-nodes-base.stopAndError","typeVersion":1,"position":[54,910],"id":"67598d54-3243-499b-b383-3692b048402b","name":"Abort — Malformed Input"},{"parameters":{"rules":{"values":[{"conditions":{"options":{"caseSensitive":true,"leftValue":"","typeValidation":"strict","version":2},"conditions":[{"id":"f4fe78e0-9705-4a36-8286-5f67d0c45bba","leftValue":"={{ $json.kind || $json.type || 'standard' }}","rightValue":"standard","operator":{"type":"string","operation":"equals"}}],"combinator":"and"},"renameOutput":true,"outputKey":"standard"},{"conditions":{"options":{"caseSensitive":true,"leftValue":"","typeValidation":"strict","version":2},"conditions":[{"id":"b58b92a4-6d69-4669-9eb7-d856ba467e7c","leftValue":"={{ $json.kind || $json.type || 'standard' }}","rightValue":"priority","operator":{"type":"string","operation":"equals"}}],"combinator":"and"},"renameOutput":true,"outputKey":"priority"}]},"options":{"fallbackOutput":"extra"}},"type":"n8n-nodes-base.switch","typeVersion":3.2,"position":[378,400],"id":"26a040bd-919c-4139-bff6-fbe8e5ce6f88","name":"Route by Work Type"},{"parameters":{"operation":"appendOrUpdate","documentId":{"__rl":true,"mode":"list","value":"","cachedResultName":"Order Tracker"},"sheetName":{"__rl":true,"mode":"name","value":"Main","cachedResultName":"Main"},"columns":{"mappingMode":"autoMapInputData","value":{},"matchingColumns":["orderId"],"schema":[]},"options":{}},"type":"n8n-nodes-base.googleSheets","typeVersion":4.7,"position":[702,130],"id":"4ac0f0c6-4a0e-49a3-8c8e-2b45fd163edd","name":"Process 'standard' → Google Sheets","retryOnFail":true,"maxTries":3,"waitBetweenTries":2000,"onError":"continueErrorOutput"},{"parameters":{"select":"channel","channelId":{"__rl":true,"mode":"name","value":"#orders","cachedResultName":"#orders"},"text":"=🚀 Priority order handled: {{ $json.orderId }}","otherOptions":{}},"type":"n8n-nodes-base.slack","typeVersion":2.3,"position":[1026,640],"id":"b3a238db-301e-4a9f-80d2-782e36b8fe0d","name":"Fast-Track 'priority' + Alert","retryOnFail":true,"maxTries":3,"waitBetweenTries":2000,"onError":"continueErrorOutput"},{"parameters":{"operation":"append","documentId":{"__rl":true,"mode":"list","value":"","cachedResultName":"Order Tracker"},"sheetName":{"__rl":true,"mode":"name","value":"Main","cachedResultName":"Main"},"columns":{"mappingMode":"autoMapInputData","value":{},"matchingColumns":[],"schema":[]},"options":{}},"type":"n8n-nodes-base.googleSheets","typeVersion":4.7,"position":[1350,1150],"id":"8ff07a51-6ec3-440f-90b7-a0c36cd7fb1d","name":"Hold Unknown Types (DLQ)","retryOnFail":true,"maxTries":3,"waitBetweenTries":2000,"onError":"continueErrorOutput"},{"parameters":{"mode":"append","numberInputs":3},"type":"n8n-nodes-base.merge","typeVersion":3.2,"position":[1998,400],"id":"f16fd40b-7615-40ef-a96d-bfe902dfb6e1","name":"Merge Routed Work"},{"parameters":{"operation":"read","documentId":{"__rl":true,"mode":"list","value":"","cachedResultName":"Order Tracker"},"sheetName":{"__rl":true,"mode":"name","value":"Main","cachedResultName":"Main"},"options":{}},"type":"n8n-nodes-base.googleSheets","typeVersion":4.7,"position":[2970,400],"id":"68aad042-356f-4d63-872a-68fc1a7d0feb","name":"Load Previous Snapshot","retryOnFail":true,"maxTries":3,"waitBetweenTries":2000,"alwaysOutputData":true,"onError":"continueErrorOutput"},{"parameters":{"mode":"runOnceForAllItems","jsCode":"// Compare current metrics with the previous snapshot\nconst current = $input.first().json;\nconst prev = $('Load Previous Snapshot').first().json || {};\nconst drift = {};\nfor (const k of Object.keys(current)) {\n  if (typeof current[k] === 'number' && typeof prev[k] === 'number' && prev[k] !== 0) {\n    drift[k] = Math.round(((current[k] - prev[k]) / prev[k]) * 1000) / 10;\n  }\n}\nreturn [{ json: { ...current, driftPct: drift, hasDrift: Object.values(drift).some(v => Math.abs(v) > 10) } }];"},"type":"n8n-nodes-base.code","typeVersion":2,"position":[3294,400],"id":"96f1c180-bdc1-4de1-9bfc-0de8a85d2f0a","name":"Compute Drift vs Snapshot"},{"parameters":{"operation":"csv","options":{}},"type":"n8n-nodes-base.convertToFile","typeVersion":1.1,"position":[3618,400],"id":"b534e257-7742-4d9b-ba68-fafa6548cdac","name":"Serialize Run Output (CSV)"},{"parameters":{"operation":"append","documentId":{"__rl":true,"mode":"list","value":"","cachedResultName":"Order Tracker"},"sheetName":{"__rl":true,"mode":"name","value":"Main","cachedResultName":"Main"},"columns":{"mappingMode":"autoMapInputData","value":{},"matchingColumns":[],"schema":[]},"options":{}},"type":"n8n-nodes-base.googleSheets","typeVersion":4.7,"position":[3942,400],"id":"de45cfc6-1d09-412b-9216-ca7b2a20ee1b","name":"Archive Row Snapshot","retryOnFail":true,"maxTries":3,"waitBetweenTries":2000,"onError":"continueErrorOutput"},{"parameters":{"mode":"runOnceForAllItems","jsCode":"// Build a stable idempotency key per order (djb2 hash, no deps)\nfunction hash(s) {\n  let h = 5381;\n  for (let i = 0; i < s.length; i++) h = ((h << 5) + h + s.charCodeAt(i)) >>> 0;\n  return h.toString(16);\n}\nreturn $input.all().map(item => {\n  const j = item.json;\n  return { json: { ...j, idempotencyKey: hash([j.orderId, j.email].join('|')) } };\n});"},"type":"n8n-nodes-base.code","typeVersion":2,"position":[4266,400],"id":"a148af22-4717-40ea-a022-0082ca937087","name":"Fingerprint for Idempotency"},{"parameters":{"operation":"removeItemsSeenInPreviousExecutions","logic":"removeItemsWithAlreadySeenKeyValues","dedupeValue":"={{ $json.idempotencyKey }}","options":{}},"type":"n8n-nodes-base.removeDuplicates","typeVersion":2,"position":[4590,400],"id":"a512ac95-7096-446a-843f-c93d4962c2f5","name":"Drop Already-Processed Items"},{"parameters":{"assignments":{"assignments":[{"id":"6905f691-1c16-42e7-aae9-a7e76d54cbf0","name":"runAt","value":"={{ $now.toISO() }}","type":"string"},{"id":"da981a8b-4624-450a-ae67-7d09d2d84efd","name":"itemCount","value":"={{ $input.all().length }}","type":"number"},{"id":"ee400f19-2f15-4f23-8ec5-57b6642df1ec","name":"status","value":"completed","type":"string"}]},"options":{}},"type":"n8n-nodes-base.set","typeVersion":3.4,"position":[4914,400],"id":"b1cc0706-7a89-4caa-b067-7bd404dd8a3b","name":"Summarize Run Stats"},{"parameters":{"operation":"append","documentId":{"__rl":true,"mode":"list","value":"","cachedResultName":"Order Tracker"},"sheetName":{"__rl":true,"mode":"name","value":"Main","cachedResultName":"Main"},"columns":{"mappingMode":"autoMapInputData","value":{},"matchingColumns":[],"schema":[]},"options":{}},"type":"n8n-nodes-base.googleSheets","typeVersion":4.7,"position":[5238,400],"id":"0afb46f7-9f62-4adf-916d-85df59a25f74","name":"Append Audit Row (Google Sheets)","retryOnFail":true,"maxTries":3,"waitBetweenTries":2000,"onError":"continueErrorOutput"},{"parameters":{"authentication":"webhook","content":"=✅ Notify stakeholders on changes with Discord on autopilot — run completed at {{ $now.toFormat('HH:mm') }}","options":{}},"type":"n8n-nodes-base.discord","typeVersion":2,"position":[5562,400],"id":"ffa162f7-0ac4-4d2e-859d-2bfce6a22357","name":"Send Summary to Discord","retryOnFail":true,"maxTries":3,"waitBetweenTries":2000,"onError":"continueErrorOutput"},{"parameters":{"assignments":{"assignments":[{"id":"cb1b0707-167f-4620-8e5b-d594e3d02f3b","name":"failedNode","value":"={{ $json.error?.node?.name || 'unknown' }}","type":"string"},{"id":"bf8afaa7-19ee-43d4-a814-a17b687c698b","name":"errorMessage","value":"={{ $json.error?.message || JSON.stringify($json).slice(0,200) }}","type":"string"},{"id":"b624bf05-190e-49b8-8d7c-b58925ae7d5e","name":"workflow","value":"={{ $workflow.name }}","type":"string"}]},"options":{}},"type":"n8n-nodes-base.set","typeVersion":3.4,"position":[4914,1420],"id":"61a5648a-6046-40fa-bb55-594d8b42a25e","name":"Capture Failure Context"},{"parameters":{"authentication":"webhook","content":"=🚨 {{ $json.workflow }} failed at {{ $json.failedNode }}: {{ $json.errorMessage }}","options":{}},"type":"n8n-nodes-base.discord","typeVersion":2,"position":[5238,1420],"id":"1f47dfc5-6b58-4347-843b-8cc0a429a5bc","name":"Escalate Failure to Discord","retryOnFail":true,"maxTries":3,"waitBetweenTries":2000},{"parameters":{"operation":"append","documentId":{"__rl":true,"mode":"list","value":"","cachedResultName":"Order Tracker"},"sheetName":{"__rl":true,"mode":"name","value":"Main","cachedResultName":"Main"},"columns":{"mappingMode":"autoMapInputData","value":{},"matchingColumns":[],"schema":[]},"options":{}},"type":"n8n-nodes-base.googleSheets","typeVersion":4.7,"position":[5562,1420],"id":"506a2dfa-d782-4b90-a1c6-c1bbfde64a0c","name":"Park in Dead-Letter Queue","retryOnFail":true,"maxTries":3,"waitBetweenTries":2000},{"parameters":{"content":"### Receive Inbound Webhook\n\nEntry point: listens for POST calls on `/wf09203-order`. Use the TEST url while building, switch callers to the PRODUCTION url after publishing.\n\nNext: Required Fields Present?","width":280,"height":232,"color":5},"type":"n8n-nodes-base.stickyNote","typeVersion":1,"position":[-330,520],"id":"ddbe5794-cf3f-6027-b154-90a5bf9444ad","name":"Note: Receive Inbound Webhook"},{"parameters":{"content":"### Required Fields Present?\n\nTwo-way gate on `={{ $json.email }}`. TRUE continues the happy path, FALSE takes the alternate branch.\n\nPorts: ①→ Route by Work Type · ②→ Abort — Malformed Input","width":280,"height":232,"color":2},"type":"n8n-nodes-base.stickyNote","typeVersion":1,"position":[-6,520],"id":"555e81f2-984a-c8ef-e4d6-fb7380ca38cf","name":"Note: Required Fields Present?"},{"parameters":{"content":"### Abort — Malformed Input\n\nFails fast with a clear message; triggers the error workflow instead of processing bad data.","width":280,"height":232,"color":2},"type":"n8n-nodes-base.stickyNote","typeVersion":1,"position":[-6,1030],"id":"ed079bd8-a751-fab1-4934-b7c736d4b282","name":"Note: Abort — Malformed Input"},{"parameters":{"content":"### Route by Work Type\n\nRoutes each item to one of 3 lanes: standard, priority + fallback.\n\nPorts: ①→ Process 'standard' → Google Sheets · ②→ Fast-Track 'priority' + Alert · ③→ Hold Unknown Types (DLQ)","width":280,"height":232,"color":2},"type":"n8n-nodes-base.stickyNote","typeVersion":1,"position":[318,520],"id":"ad146a08-ea26-3fe0-29a9-6ee156729c21","name":"Note: Route by Work Type"},{"parameters":{"content":"### Process 'standard' → Google Sheets\n\ngoogleSheets — `appendOrUpdate` operation against the connected account.\n\nPorts: ①→ Merge Routed Work · ②→ Capture Failure Context\n\n↻ retries 3×/2s · ⚠ failures exit via the error rail · 🔑 Google OAuth2 / service account","width":280,"height":232,"color":2},"type":"n8n-nodes-base.stickyNote","typeVersion":1,"position":[642,250],"id":"8e70fef8-1e28-630d-44f8-c63616f0741e","name":"Note: Process 'standard' → Google Sheets"},{"parameters":{"content":"### Fast-Track 'priority' + Alert\n\nslack — `action` operation against the connected account.\n\nPorts: ①→ Merge Routed Work · ②→ Capture Failure Context\n\n↻ retries 3×/2s · ⚠ failures exit via the error rail · 🔑 Slack OAuth2","width":280,"height":232,"color":2},"type":"n8n-nodes-base.stickyNote","typeVersion":1,"position":[966,760],"id":"79cd5745-d9d4-b850-2dcf-b294d4aae34d","name":"Note: Fast-Track 'priority' + Alert"},{"parameters":{"content":"### Hold Unknown Types (DLQ)\n\ngoogleSheets — `append` operation against the connected account.\n\nPorts: ①→ Merge Routed Work · ②→ Capture Failure Context\n\n↻ retries 3×/2s · ⚠ failures exit via the error rail · 🔑 Google OAuth2 / service account","width":280,"height":232,"color":2},"type":"n8n-nodes-base.stickyNote","typeVersion":1,"position":[1290,1270],"id":"5a00609c-86d7-e016-326c-d44fc3eefc1e","name":"Note: Hold Unknown Types (DLQ)"},{"parameters":{"content":"### Merge Routed Work\n\nRejoins 3 branches into one stream (mode: append) so downstream logic runs once.\n\nNext: Load Previous Snapshot","width":280,"height":232,"color":7},"type":"n8n-nodes-base.stickyNote","typeVersion":1,"position":[1938,520],"id":"2f06c2e1-75f3-5ef4-6708-e9a22b42567a","name":"Note: Merge Routed Work"},{"parameters":{"content":"### Load Previous Snapshot\n\ngoogleSheets — `read` operation against the connected account.\n\nPorts: ①→ Compute Drift vs Snapshot · ②→ Capture Failure Context\n\n↻ retries 3×/2s · ⚠ failures exit via the error rail · 🔑 Google OAuth2 / service account","width":280,"height":232,"color":2},"type":"n8n-nodes-base.stickyNote","typeVersion":1,"position":[2910,520],"id":"9a968a35-11c0-a8de-b1a3-1d3e60c96151","name":"Note: Load Previous Snapshot"},{"parameters":{"content":"### Compute Drift vs Snapshot\n\nCustom JavaScript: Compare current metrics with the previous snapshot\n\nNext: Serialize Run Output (CSV)","width":280,"height":232,"color":7},"type":"n8n-nodes-base.stickyNote","typeVersion":1,"position":[3234,520],"id":"a2b4d682-290a-c922-7f30-673f9a29a0d7","name":"Note: Compute Drift vs Snapshot"},{"parameters":{"content":"### Serialize Run Output (CSV)\n\nSerializes items to a CSV binary file.\n\nNext: Archive Row Snapshot","width":280,"height":232,"color":2},"type":"n8n-nodes-base.stickyNote","typeVersion":1,"position":[3558,520],"id":"11e389c7-d824-4af9-228c-35dee8ae4c91","name":"Note: Serialize Run Output (CSV)"},{"parameters":{"content":"### Archive Row Snapshot\n\ngoogleSheets — `append` operation against the connected account.\n\nPorts: ①→ Fingerprint for Idempotency · ②→ Capture Failure Context\n\n↻ retries 3×/2s · ⚠ failures exit via the error rail · 🔑 Google OAuth2 / service account","width":280,"height":232,"color":2},"type":"n8n-nodes-base.stickyNote","typeVersion":1,"position":[3882,520],"id":"08263900-4758-cf33-fffb-ecfc435aee80","name":"Note: Archive Row Snapshot"},{"parameters":{"content":"### Fingerprint for Idempotency\n\nCustom JavaScript: Build a stable idempotency key per order (djb2 hash, no deps)\n\nNext: Drop Already-Processed Items","width":280,"height":232,"color":7},"type":"n8n-nodes-base.stickyNote","typeVersion":1,"position":[4206,520],"id":"5eaaea1a-1707-d499-8dcf-53471a99ef52","name":"Note: Fingerprint for Idempotency"},{"parameters":{"content":"### Drop Already-Processed Items\n\nCross-execution dedupe: remembers keys it has processed before and drops repeats — the idempotency guard.\n\nNext: Summarize Run Stats","width":280,"height":232,"color":2},"type":"n8n-nodes-base.stickyNote","typeVersion":1,"position":[4530,520],"id":"f1f49652-d6cd-2a32-02f5-d32ce1f6f3da","name":"Note: Drop Already-Processed Items"},{"parameters":{"content":"### Summarize Run Stats\n\nShapes the item: writes `runAt`, `itemCount`, `status`. Keeps the schema explicit between stages.\n\nNext: Append Audit Row (Google Sheets)","width":280,"height":232,"color":7},"type":"n8n-nodes-base.stickyNote","typeVersion":1,"position":[4854,520],"id":"de1a0ec2-8dc9-db28-f356-350dbff1a235","name":"Note: Summarize Run Stats"},{"parameters":{"content":"### Append Audit Row (Google Sheets)\n\ngoogleSheets — `append` operation against the connected account.\n\nPorts: ①→ Send Summary to Discord · ②→ Capture Failure Context\n\n↻ retries 3×/2s · ⚠ failures exit via the error rail · 🔑 Google OAuth2 / service account","width":280,"height":232,"color":2},"type":"n8n-nodes-base.stickyNote","typeVersion":1,"position":[5178,520],"id":"c4285ab5-91f8-b159-cb88-715be7c83e0d","name":"Note: Append Audit Row (Google Sheets)"},{"parameters":{"content":"### Send Summary to Discord\n\ndiscord — `action` operation against the connected account.\n\n↻ retries 3×/2s · ⚠ failures exit via the error rail · 🔑 Discord webhook URL","width":280,"height":232,"color":4},"type":"n8n-nodes-base.stickyNote","typeVersion":1,"position":[5502,520],"id":"ee499f44-0083-4306-062c-dcded97410c3","name":"Note: Send Summary to Discord"},{"parameters":{"content":"### Capture Failure Context\n\nShapes the item: writes `failedNode`, `errorMessage`, `workflow`. Keeps the schema explicit between stages.\n\nNext: Escalate Failure to Discord","width":280,"height":232,"color":3},"type":"n8n-nodes-base.stickyNote","typeVersion":1,"position":[4854,1540],"id":"71a23113-c451-1cdf-ef88-cb971eb05491","name":"Note: Capture Failure Context"},{"parameters":{"content":"### Escalate Failure to Discord\n\ndiscord — `action` operation against the connected account.\n\nNext: Park in Dead-Letter Queue\n\n↻ retries 3×/2s · 🔑 Discord webhook URL","width":280,"height":232,"color":3},"type":"n8n-nodes-base.stickyNote","typeVersion":1,"position":[5178,1540],"id":"421bd844-a7d5-a8b5-1f9c-fca57f9c2333","name":"Note: Escalate Failure to Discord"},{"parameters":{"content":"### Park in Dead-Letter Queue\n\ngoogleSheets — `append` operation against the connected account.\n\n↻ retries 3×/2s · 🔑 Google OAuth2 / service account","width":280,"height":232,"color":3},"type":"n8n-nodes-base.stickyNote","typeVersion":1,"position":[5502,1540],"id":"d2c2e5e6-321a-879f-1bfc-c11a548c1c1e","name":"Note: Park in Dead-Letter Queue"},{"parameters":{"content":"# Notify stakeholders on changes with Discord on autopilot\n\n**Pattern:** Event Notification · **Level:** Production · **Trigger:** Webhook\n\n## What it does\nNotify stakeholders on changes with Discord on autopilot. It fires the moment an external system calls its webhook.\n\n## Why it exists\nManual inventory is slow and error-prone; this workflow makes the process repeatable, monitored and hands-off, with failures surfaced instead of silently lost.\n\n## Main flow\nReceive Inbound Webhook → Required Fields Present? → Route by Work Type → Process 'standard' → Google Sheets → Merge Routed Work → Load Previous Snapshot → Compute Drift vs Snapshot → …\n\n## Use it for\n- Teams that want to event notification without manual effort\n- Anyone automating inventory in e-commerce\n- Replacing a fragile manual process with a reliable workflow\n\n## You get\n- Has retries and error handling built in\n- Removes copy-paste errors\n- Saves hours of manual work each week\n\n## Before first run\nConnect credentials: Discord webhook URL; Google OAuth2 / service account; Slack OAuth2.\nFollow the color key: 🟦 entry · 🟪 AI · 🟫 actions · ⬜ utilities · 🟩 outputs · 🟥 error rail.\nEach node has its own doc card underneath — read those before editing.","width":480,"height":900},"type":"n8n-nodes-base.stickyNote","typeVersion":1,"position":[-830,80],"id":"bfbd1a1a-02d1-202b-f182-f4f6f92d4205","name":"📘 Workflow Overview"},{"parameters":{"content":"## 🛟 Error handling & retries\n\nExternal calls retry **3× with 2s backoff**. Anything still failing exits through its node's error output into the red error rail → context is captured and the on-call channel is alerted. Failures are also parked in a dead-letter queue for replay. Set an n8n **Error Workflow** in settings as the final safety net.","width":360,"height":260,"color":3},"type":"n8n-nodes-base.stickyNote","typeVersion":1,"position":[-230,-290],"id":"6b2e94b8-77d3-a982-393a-8cba9d7ee1fb","name":"🛟 Error handling & retries"},{"parameters":{"content":"## 🔐 Security\n\nNever trust inbound payloads: the webhook path is unguessable. Add header auth or IP allow-listing for defense in depth. Secrets live in n8n credentials — never in node parameters.","width":360,"height":260,"color":1},"type":"n8n-nodes-base.stickyNote","typeVersion":1,"position":[190,-290],"id":"f96a3644-111e-de96-fb51-d90d5744a0b4","name":"🔐 Security"},{"parameters":{"content":"## 🧹 Data quality\n\nDedupe/diff steps make re-runs safe: the same input twice will not create duplicate records. If you change the key fields, clear n8n's dedupe memory (node → 'Clear stored keys') before the next run.","width":360,"height":260,"color":1},"type":"n8n-nodes-base.stickyNote","typeVersion":1,"position":[610,-290],"id":"678bb793-3a50-d5ca-5f9f-6b3cef6746c0","name":"🧹 Data quality"},{"parameters":{"content":"## 🛠 Customize me\n\nQuick wins: point the data nodes at your own accounts (see 🔑 lines on each card), adjust the trigger cadence, and tune thresholds/labels to your inventory process. Every node card explains its role — safe to extend at any marked branch.","width":360,"height":260,"color":4},"type":"n8n-nodes-base.stickyNote","typeVersion":1,"position":[1030,-290],"id":"318dd69f-4ba1-513a-51b8-7d6ae60c52a1","name":"🛠 Customize me"}],"connections":{"Receive Inbound Webhook":{"main":[[{"node":"Required Fields Present?","type":"main","index":0}]]},"Required Fields Present?":{"main":[[{"node":"Route by Work Type","type":"main","index":0}],[{"node":"Abort — Malformed Input","type":"main","index":0}]]},"Route by Work Type":{"main":[[{"node":"Process 'standard' → Google Sheets","type":"main","index":0}],[{"node":"Fast-Track 'priority' + Alert","type":"main","index":0}],[{"node":"Hold Unknown Types (DLQ)","type":"main","index":0}]]},"Process 'standard' → Google Sheets":{"main":[[{"node":"Merge Routed Work","type":"main","index":0}],[{"node":"Capture Failure Context","type":"main","index":0}]]},"Fast-Track 'priority' + Alert":{"main":[[{"node":"Merge Routed Work","type":"main","index":1}],[{"node":"Capture Failure Context","type":"main","index":0}]]},"Hold Unknown Types (DLQ)":{"main":[[{"node":"Merge Routed Work","type":"main","index":2}],[{"node":"Capture Failure Context","type":"main","index":0}]]},"Merge Routed Work":{"main":[[{"node":"Load Previous Snapshot","type":"main","index":0}]]},"Load Previous Snapshot":{"main":[[{"node":"Compute Drift vs Snapshot","type":"main","index":0}],[{"node":"Capture Failure Context","type":"main","index":0}]]},"Compute Drift vs Snapshot":{"main":[[{"node":"Serialize Run Output (CSV)","type":"main","index":0}]]},"Serialize Run Output (CSV)":{"main":[[{"node":"Archive Row Snapshot","type":"main","index":0}]]},"Archive Row Snapshot":{"main":[[{"node":"Fingerprint for Idempotency","type":"main","index":0}],[{"node":"Capture Failure Context","type":"main","index":0}]]},"Fingerprint for Idempotency":{"main":[[{"node":"Drop Already-Processed Items","type":"main","index":0}]]},"Drop Already-Processed Items":{"main":[[{"node":"Summarize Run Stats","type":"main","index":0}]]},"Summarize Run Stats":{"main":[[{"node":"Append Audit Row (Google Sheets)","type":"main","index":0}]]},"Append Audit Row (Google Sheets)":{"main":[[{"node":"Send Summary to Discord","type":"main","index":0}],[{"node":"Capture Failure Context","type":"main","index":0}]]},"Capture Failure Context":{"main":[[{"node":"Escalate Failure to Discord","type":"main","index":0}]]},"Escalate Failure to Discord":{"main":[[{"node":"Park in Dead-Letter Queue","type":"main","index":0}]]},"Send Summary to Discord":{"main":[[],[{"node":"Capture Failure Context","type":"main","index":0}]]}},"active":false,"settings":{"executionOrder":"v1"},"meta":{"templateCredsSetupCompleted":false},"tags":[],"pinData":{},"versionId":"294a6586-569a-41f1-a9f8-dff5d207890d","id":"FDX09203"}